dashboardspot/__init__.py
dashboardspot-0.9.1.dist-info/METADATA
dashboardspot-0.9.1.dist-info/WHEEL
dashboardspot-0.9.1.dist-info/top_level.txt
dashboardspot-0.9.1.dist-info/RECORD
