Metadata-Version: 2.1
Name: dashboardspot
Version: 0.9.1
Summary: DashboardSpot pyhon library.
Home-page: https://github.com/terrillo/dashboardspot-python
Author: Terrillo Walls
Author-email: terrillo@terrillo.com
License: UNKNOWN
Project-URL: Bug Tracker, https://github.com/terrillo/dashboardspot-python/issues
Project-URL: Documentation, https://github.com/terrillo/dashboardspot-python
Project-URL: Source Code, https://github.com/terrillo/dashboardspot-python
Platform: UNKNOWN
Classifier: Programming Language :: Python :: 3
Classifier: License :: OSI Approved :: MIT License
Classifier: Operating System :: OS Independent
Requires-Python: >=3.0.*
Requires-Dist: requests
